mona_openai/__init__.py
mona_openai/exceptions.py
mona_openai/mona_openai_client.py
mona_openai/mona_openai_create.py
mona_openai/mona_openai_legacy.py
mona_openai/mona_openai_logging.py
mona_openai/analysis/analyzer.py
mona_openai/analysis/privacy.py
mona_openai/analysis/profanity.py
mona_openai/analysis/textual.py
mona_openai/analysis/util.py
mona_openai/endpoints/chat_completion.py
mona_openai/endpoints/completion.py
mona_openai/endpoints/endpoint_wrapping.py
mona_openai/endpoints/wrapping_getter.py
mona_openai/loggers/__init__.py
mona_openai/loggers/file_logger.py
mona_openai/loggers/in_memory_logging.py
mona_openai/loggers/logger.py
mona_openai/loggers/standard_logging.py
mona_openai/loggers/mona_logger/mona_client.py
mona_openai/loggers/mona_logger/mona_logger.py
mona_openai/util/async_util.py
mona_openai/util/func_util.py
mona_openai/util/general_consts.py
mona_openai/util/object_util.py
mona_openai/util/openai_util.py
mona_openai/util/stream_util.py
mona_openai/util/tokens_util.py
mona_openai/util/typing_util.py
mona_openai/util/validation_util.py
mona_openai-0.2.1.dist-info/LICENSE
mona_openai-0.2.1.dist-info/METADATA
mona_openai-0.2.1.dist-info/WHEEL
mona_openai-0.2.1.dist-info/top_level.txt
mona_openai-0.2.1.dist-info/RECORD
