Metadata-Version: 2.1
Name: mona-openai
Version: 0.2.1
Summary: Integration client for monitoring OpenAI usage with Mona
Author-email: Itai Bar Sinai <itai@monalabs.io>
Project-URL: Homepage, https://github.com/monalabs/mona-openai
Project-URL: Bug Tracker, https://github.com/monalabs/mona-openai/issues
Keywords: OpenAI,LLMs,GPT,Mona,Monitoring,AI
Classifier: Programming Language :: Python :: 3
Classifier: License :: OSI Approved :: Apache Software License
Classifier: Operating System :: OS Independent
Requires-Python: >=3.9
License-File: LICENSE
Requires-Dist: mona-sdk >=0.0.49
Requires-Dist: alt-profanity-check >=1.2.2
Requires-Dist: phonenumberslite >=8.13.7
Requires-Dist: tiktoken >=0.3.3
Requires-Dist: nest-asyncio >=1.5.6
